portainer_ctl/__init__.py
portainer_ctl/api.py
portainer_ctl/cli.py
portainer_ctl/client.py
portainer_ctl/errors.py
portainer_ctl/helpers.py
portainer_ctl/models.py
portainer_ctl/printer.py
portainer_ctl-0.2.1.dist-info/METADATA
portainer_ctl-0.2.1.dist-info/WHEEL
portainer_ctl-0.2.1.dist-info/entry_points.txt
portainer_ctl-0.2.1.dist-info/licenses/LICENSE
portainer_ctl-0.2.1.dist-info/RECORD
