Metadata-Version: 2.4
Name: portainer-ctl
Version: 0.2.1
Summary: A poor man's kubectl for docker swarm
Author: Hossein Naderi
License-Expression: Apache-2.0
License-File: LICENSE
Keywords: docker,docker swarm,kubectl,portainer,swarm
Requires-Python: >=3.8
Requires-Dist: requests<3,>=2.31.0
Requires-Dist: rich-argparse>=1.7.0
Requires-Dist: rich>=14.0.0
